autobot/__init__.py
autobot/__main__.py
autobot/api.py
autobot/main.py
autobot/prompt.py
autobot/py.typed
autobot/refactor/__init__.py
autobot/refactor/patches.py
autobot/refactor/refactor.py
autobot/review/__init__.py
autobot/review/review.py
autobot/schematic.py
autobot/schematics/assert_equals/after.py
autobot/schematics/assert_equals/before.py
autobot/schematics/convert_to_dataclass/after.py
autobot/schematics/convert_to_dataclass/before.py
autobot/schematics/numpy_builtin_aliases/after.py
autobot/schematics/numpy_builtin_aliases/before.py
autobot/schematics/print_statement/after.py
autobot/schematics/print_statement/before.py
autobot/schematics/sorted_attributes/after.py
autobot/schematics/sorted_attributes/before.py
autobot/schematics/standard_library_generics/after.py
autobot/schematics/standard_library_generics/before.py
autobot/schematics/unnecessary_f_strings/after.py
autobot/schematics/unnecessary_f_strings/before.py
autobot/schematics/use_generator/after.py
autobot/schematics/use_generator/before.py
autobot/schematics/useless_object_inheritance/after.py
autobot/schematics/useless_object_inheritance/before.py
autobot/snippet.py
autobot/transforms.py
autobot/utils/__init__.py
autobot/utils/cache.py
autobot/utils/filesystem.py
autobot/utils/getch.py
autobot/version.py
autobot_ml-0.0.16.dist-info/entry_points.txt
autobot_ml-0.0.16.dist-info/LICENSE
autobot_ml-0.0.16.dist-info/WHEEL
autobot_ml-0.0.16.dist-info/METADATA
autobot_ml-0.0.16.dist-info/RECORD
