Metadata-Version: 2.1
Name: autobot-ml
Version: 0.0.16
Summary: An automated code refactoring tool powered by GPT-3.
Home-page: https://github.com/charliermarsh/autobot
License: MIT
Author: Charlie Marsh
Author-email: charlie.r.marsh@gmail.com
Requires-Python: >=3.8,<3.11
Classifier: Development Status :: 3 - Alpha
Classifier: Environment :: Console
Classifier: Intended Audience :: Developers
Classifier: License :: OSI Approved :: MIT License
Classifier: Operating System :: OS Independent
Classifier: Programming Language :: Python
Classifier: Programming Language :: Python :: 3
Classifier: Programming Language :: Python :: 3.8
Classifier: Programming Language :: Python :: 3.9
Classifier: Programming Language :: Python :: 3.10
Classifier: Programming Language :: Python :: 3 :: Only
Classifier: Programming Language :: Python :: 3.10
Classifier: Programming Language :: Python :: 3.8
Classifier: Programming Language :: Python :: 3.9
Classifier: Topic :: Software Development :: Libraries :: Python Modules
Classifier: Topic :: Software Development :: Quality Assurance
Requires-Dist: colorama (>=0.4.5,<0.5.0)
Requires-Dist: openai (>=0.23.0,<0.24.0)
Requires-Dist: python-dotenv (>=0.21.0,<0.22.0)
Requires-Dist: rich (>=12.5.1,<13.0.0)
Project-URL: Repository, https://github.com/charliermarsh/autobot
